CONTACT
LICENCE
MANIFEST.in
README.txt
dptMakefile
dptversion.py
extend_dptapi_python
licence.txt
setup.py
dpt3.0_dptdb.egg-info/PKG-INFO
dpt3.0_dptdb.egg-info/SOURCES.txt
dpt3.0_dptdb.egg-info/dependency_links.txt
dpt3.0_dptdb.egg-info/not-zip-safe
dpt3.0_dptdb.egg-info/top_level.txt
dptdb/__init__.py
test/pydpt-test.py