Metadata-Version: 2.1
Name: dpt3.0-dptdb
Version: 0.8.2
Summary: DPT database API wrappers built using SWIG
Home-page: http://www.solentware.co.uk
Author: Roger Marsh
Author-email: roger.marsh@solentware.co.uk
License: BSD
Platform: Microsoft Windows
Classifier: License :: OSI Approved :: BSD License
Classifier: Programming Language :: Python
Classifier: Operating System :: Microsoft :: Windows
Classifier: Topic :: Database
Classifier: Topic :: Software Development
Classifier: Intended Audience :: Developers
Classifier: Development Status :: 7 - Inactive
License-File: LICENCE
License-File: licence.txt
